jupyter_dash/__init__.py
jupyter_dash/_stoppable_thread.py
jupyter_dash/comms.py
jupyter_dash/jupyter_app.py
jupyter_dash/version.py
jupyter_dash/labextension/package.json
jupyter_dash/labextension/dist/jupyterlab-dash-v0.4.1.tgz
jupyter_dash/labextension/dist/jupyterlab-dash-v0.4.2.tgz
jupyter_dash/nbextension/jupyter_dash.json
jupyter_dash/nbextension/main.js
jupyter_dash-0.4.2.data/data/etc/jupyter/nbconfig/notebook.d/jupyter_dash.json
jupyter_dash-0.4.2.data/data/share/jupyter/lab/extensions/jupyterlab-dash-v0.4.2.tgz
jupyter_dash-0.4.2.data/data/share/jupyter/nbextensions/jupyter_dash/main.js
jupyter_dash-0.4.2.dist-info/LICENSE.txt
jupyter_dash-0.4.2.dist-info/METADATA
jupyter_dash-0.4.2.dist-info/WHEEL
jupyter_dash-0.4.2.dist-info/top_level.txt
jupyter_dash-0.4.2.dist-info/RECORD
