Metadata-Version: 2.1
Name: jupyter-dash
Version: 0.4.2
Summary: Dash support for the Jupyter notebook interface
Home-page: https://github.com/plotly/jupyter-dash
Author: Plotly
License: MIT
Project-URL: Github, https://github.com/plotly/jupyter-dash
Platform: UNKNOWN
Requires-Python: >=3.5
Provides-Extra: dev
License-File: LICENSE.txt
